{"magnemite":55,"atreelessplain":53,"galactoast":41,"rabbitcereal":27,"not_a_price_tag":21,"juryvgc":13,"minyanouvelle":11,"pricetagsh":11,"miggtorr":11,"kreemari":7,"epoic_alien8":5,"tquick101":5,"mrmodeishere":4,"gregster022":4,"silverbarber":4,"thepirkachu":3,"RabbitCereal":3,"laughhere":3,"danjaymmkay":3,"hayzelnoot":3,"PokePlayz2020":2,"jinglesthepyro":2,"witchniko":2,"sparky129_official":2,"jumbledjamies94":2,"bugma5t3r":1,"xdan993x":1,"mintkori":1,"leafeon03":1,"mysticrainbowdragon":1,"exeat1":0,"MotionlessFlame":0,"MintKori":0,"xlilscruffyx":0,"firepiplup":0,"pokeplayz2020":0,"cdlfrgt":0,"kwikpanik":0,"schrafdaddy":0}